odoo/addons/stock_orderpoint_manual_procurement/README.rst
odoo/addons/stock_orderpoint_manual_procurement/__init__.py
odoo/addons/stock_orderpoint_manual_procurement/__manifest__.py
odoo/addons/stock_orderpoint_manual_procurement/demo/product.xml
odoo/addons/stock_orderpoint_manual_procurement/models/__init__.py
odoo/addons/stock_orderpoint_manual_procurement/models/stock_warehouse_orderpoint.py
odoo/addons/stock_orderpoint_manual_procurement/security/stock_orderpoint_manual_procurement_security.xml
odoo/addons/stock_orderpoint_manual_procurement/static/description/icon.png
odoo/addons/stock_orderpoint_manual_procurement/tests/__init__.py
odoo/addons/stock_orderpoint_manual_procurement/tests/test_stock_orderpoint_manual_procurement.py
odoo/addons/stock_orderpoint_manual_procurement/views/stock_warehouse_orderpoint_view.xml
odoo/addons/stock_orderpoint_manual_procurement/wizards/__init__.py
odoo/addons/stock_orderpoint_manual_procurement/wizards/make_procurement_orderpoint.py
odoo/addons/stock_orderpoint_manual_procurement/wizards/make_procurement_orderpoint_view.xml
odoo11_addon_stock_orderpoint_manual_procurement-11.0.1.1.1.dist-info/DESCRIPTION.rst
odoo11_addon_stock_orderpoint_manual_procurement-11.0.1.1.1.dist-info/METADATA
odoo11_addon_stock_orderpoint_manual_procurement-11.0.1.1.1.dist-info/RECORD
odoo11_addon_stock_orderpoint_manual_procurement-11.0.1.1.1.dist-info/WHEEL
odoo11_addon_stock_orderpoint_manual_procurement-11.0.1.1.1.dist-info/metadata.json
odoo11_addon_stock_orderpoint_manual_procurement-11.0.1.1.1.dist-info/top_level.txt
